README.txt
plonetheme.essay-configure.zcml
setup.cfg
setup.py
docs/HISTORY.txt
docs/INSTALL.txt
docs/LICENSE.GPL
docs/LICENSE.txt
plonetheme/__init__.py
plonetheme.essay.egg-info/PKG-INFO
plonetheme.essay.egg-info/SOURCES.txt
plonetheme.essay.egg-info/dependency_links.txt
plonetheme.essay.egg-info/entry_points.txt
plonetheme.essay.egg-info/namespace_packages.txt
plonetheme.essay.egg-info/not-zip-safe
plonetheme.essay.egg-info/requires.txt
plonetheme.essay.egg-info/top_level.txt
plonetheme/essay/__init__.py
plonetheme/essay/configure.zcml
plonetheme/essay/profiles.zcml
plonetheme/essay/setuphandlers.py
plonetheme/essay/skins.zcml
plonetheme/essay/tests.py
plonetheme/essay/version.txt
plonetheme/essay/browser/__init__.py
plonetheme/essay/browser/configure.zcml
plonetheme/essay/browser/interfaces.py
plonetheme/essay/browser/viewlet.pt
plonetheme/essay/browser/viewlets.py
plonetheme/essay/browser/images/README.txt
plonetheme/essay/browser/stylesheets/.main.css.dtml.swp
plonetheme/essay/browser/stylesheets/README.txt
plonetheme/essay/browser/stylesheets/main.css
plonetheme/essay/browser/stylesheets/main.css.dtml
plonetheme/essay/profiles/default/.viewlets.xml.swp
plonetheme/essay/profiles/default/cssregistry.xml
plonetheme/essay/profiles/default/import_steps.xml
plonetheme/essay/profiles/default/jsregistry.xml
plonetheme/essay/profiles/default/plonetheme.essay_various.txt
plonetheme/essay/profiles/default/skins.xml
plonetheme/essay/profiles/default/viewlets.xml
plonetheme/essay/skins/plonetheme_essay_custom_images/CONTENT.txt
plonetheme/essay/skins/plonetheme_essay_custom_images/logo.jpg
plonetheme/essay/skins/plonetheme_essay_custom_templates/CONTENT.txt
plonetheme/essay/skins/plonetheme_essay_custom_templates/main_template.pt
plonetheme/essay/skins/plonetheme_essay_styles/CONTENT.txt
plonetheme/essay/skins/plonetheme_essay_styles/base_properties.props
plonetheme/essay/skins/plonetheme_essay_styles/ploneCustom.css.dtml
plonetheme/essay/skins/plonetheme_essay_styles/ploneCustom.css.dtml.metadata
